sqd_song_edit/__init__.py
sqd_song_edit/__main__.py
sqd_song_edit/color.py
sqd_song_edit/errors.py
sqd_song_edit/start.py
sqd_song_edit/utils.py
sqd_song_edit-1.1.2.dist-info/LICENSE
sqd_song_edit-1.1.2.dist-info/METADATA
sqd_song_edit-1.1.2.dist-info/WHEEL
sqd_song_edit-1.1.2.dist-info/entry_points.txt
sqd_song_edit-1.1.2.dist-info/top_level.txt
sqd_song_edit-1.1.2.dist-info/RECORD
