Metadata-Version: 2.1
Name: sqd-song-edit
Version: 1.1.2
Summary: edit song cover art and metadeta easily!
Author: sqdnoises
License: The MIT License (MIT)
Classifier: Programming Language :: Python :: 3
Classifier: License :: OSI Approved :: MIT License
Classifier: Operating System :: OS Independent
Requires-Python: >=3.8
License-File: LICENSE
Requires-Dist: eyeD3
Requires-Dist: luddite
Requires-Dist: sqdconvert
Requires-Dist: mutagen
Provides-Extra: dev
Requires-Dist: pip-tools ; extra == 'dev'
Requires-Dist: build ; extra == 'dev'
Requires-Dist: twine ; extra == 'dev'
Provides-Extra: windows
Requires-Dist: pyreadline3 ; extra == 'windows'
